[
    {
        "question": "What was added in Comfyroll Studio version 1.76?",
        "answer": "In version 1.76 of Comfyroll Studio, CR VAE Decode, CR Combine Prompt, and CR Diamond Pattern were added."
    },
    {
        "question": "What was fixed in Comfyroll Studio version 1.75.1?",
        "answer": "In version 1.75.1 of Comfyroll Studio, a fix was made for issue 112 CR Text Blacklist, which involved adding handling for blank lines and fixing an issue with finding multiple keywords. Additionally, PR108 addressed a fix for a missing import in nodes_utils_text.py."
    },
    {
        "question": "What was added in Comfyroll Studio version 1.75?",
        "answer": "In version 1.75 of Comfyroll Studio, CR Half Drop Panel was added."
    },
    {
        "question": "What was fixed in Comfyroll Studio version 1.74.1?",
        "answer": "In version 1.74.1 of Comfyroll Studio, the show_help function of CR Thumbnail Preview was fixed."
    },
    {
        "question": "What updates were made to CR Simple Image Compare in version 1.74?",
        "answer": "In version 1.74 of Comfyroll Studio, CR Simple Image Compare was updated to automatically resize the second image if its size differed from the first."
    },
    {
        "question": "What was added in Comfyroll Studio version 1.74?",
        "answer": "In version 1.74 of Comfyroll Studio, CR Aspect Ratio For Print, CR Seamless Checker, and CR Select ISO Size were added."
    },
    {
        "question": "What was addressed in Comfyroll Studio version 1.73.1?",
        "answer": "Comfyroll Studio version 1.73.1 included a fix for issue 104."
    }
]