[
    {
        "question": "What is the purpose of the easy imageCount node in ComfyUI?",
        "answer": "The easy imageCount node is designed to count the number of images in a given batch, providing an intuitive way to quantify image collections in a workflow."
    },
    {
        "question": "What is the required input type for the easy imageCount node?",
        "answer": "The required input type for the easy imageCount node is 'images', which represents the batch of images to be counted."
    },
    {
        "question": "What Comfy dtype does the 'images' input parameter use?",
        "answer": "The 'images' input parameter uses the Comfy dtype 'IMAGE'."
    },
    {
        "question": "What Python dtype does the 'images' input parameter correspond to?",
        "answer": "The 'images' input parameter corresponds to the Python dtype 'torch.Tensor'."
    },
    {
        "question": "What is the output type of the easy imageCount node?",
        "answer": "The output type of the easy imageCount node is 'count', which represents the total number of images in the input batch."
    },
    {
        "question": "What Comfy dtype does the 'count' output use?",
        "answer": "The 'count' output uses the Comfy dtype 'INT'."
    },
    {
        "question": "What Python dtype does the 'count' output correspond to?",
        "answer": "The 'count' output corresponds to the Python dtype 'int'."
    }
]