[
    {
        "question": "What is the class name of the JWIntegerAdd node?",
        "answer": "The class name of the JWIntegerAdd node is 'JWIntegerAdd'."
    },
    {
        "question": "Which category does the JWIntegerAdd node belong to?",
        "answer": "The JWIntegerAdd node belongs to the 'jamesWalker55' category."
    },
    {
        "question": "Is JWIntegerAdd an output node?",
        "answer": "No, the JWIntegerAdd node is not an output node. It is indicated as 'False' in the documentation."
    },
    {
        "question": "What are the required input types for the JWIntegerAdd node?",
        "answer": "The required input types for the JWIntegerAdd node are 'a' and 'b', both of which are integers."
    },
    {
        "question": "What does the 'a' input represent in the JWIntegerAdd node?",
        "answer": "The 'a' input represents the first integer value to be added in the JWIntegerAdd node."
    },
    {
        "question": "What does the 'b' input represent in the JWIntegerAdd node?",
        "answer": "The 'b' input represents the second integer value to be added in the JWIntegerAdd node."
    },
    {
        "question": "What is the output type of the JWIntegerAdd node?",
        "answer": "The output type of the JWIntegerAdd node is 'int', which represents the sum of the two input integers."
    },
    {
        "question": "What is the infra type of the JWIntegerAdd node?",
        "answer": "The infra type of the JWIntegerAdd node is 'CPU'."
    }
]