[
    {
        "question": "What is the class name of the IntegerNode in ComfyUI?",
        "answer": "The class name of the IntegerNode is 'IntegerNode'."
    },
    {
        "question": "Which category does the IntegerNode belong to in ComfyUI?",
        "answer": "The IntegerNode belongs to the '😺dzNodes/LayerUtility/Data' category in ComfyUI."
    },
    {
        "question": "Is IntegerNode an output node in ComfyUI?",
        "answer": "No, IntegerNode is not an output node in ComfyUI."
    },
    {
        "question": "What is the required input type for IntegerNode?",
        "answer": "The required input type for IntegerNode is 'int_value', which is of type INT."
    },
    {
        "question": "What does the 'int_value' input represent in IntegerNode?",
        "answer": "The 'int_value' input represents an integer value in IntegerNode."
    },
    {
        "question": "What is the output type of IntegerNode?",
        "answer": "The output type of IntegerNode is 'int', which is of type INT."
    },
    {
        "question": "What is the infra type for IntegerNode?",
        "answer": "The infra type for IntegerNode is CPU."
    }
]