[
    {
        "question": "What is the purpose of the SoftLight class in ComfyUI?",
        "answer": "The SoftLight class in ComfyUI is used to apply a soft light effect to images."
    },
    {
        "question": "What are the required input types for the SoftLight class?",
        "answer": "The required input types for the SoftLight class are: image (torch.Tensor), soft (float), threshold (int), and opacity (int)."
    },
    {
        "question": "What does the 'soft' parameter control in the SoftLight class?",
        "answer": "The 'soft' parameter in the SoftLight class controls the amount of blur applied to the image."
    },
    {
        "question": "What does the 'threshold' parameter control in the SoftLight class?",
        "answer": "The 'threshold' parameter in the SoftLight class controls the highlight threshold for the image."
    },
    {
        "question": "What does the 'opacity' parameter control in the SoftLight class?",
        "answer": "The 'opacity' parameter in the SoftLight class controls the transparency of the soft light effect applied to the image."
    },
    {
        "question": "What is the output type of the SoftLight class?",
        "answer": "The output type of the SoftLight class is an image (torch.Tensor)."
    },
    {
        "question": "Which infra type is recommended for running the SoftLight class?",
        "answer": "The recommended infra type for running the SoftLight class is CPU."
    }
]