[
    {
        "question": "What is ComfyUI-seam-carving?",
        "answer": "ComfyUI-seam-carving is a plugin for ComfyUI that provides image resizing capability using the seam carving technique."
    },
    {
        "question": "What node does ComfyUI-seam-carving add to ComfyUI?",
        "answer": "ComfyUI-seam-carving adds a node called 'Image Resize (seam carving)' to ComfyUI."
    },
    {
        "question": "What is seam carving?",
        "answer": "Seam carving is an algorithm that allows an image to be re-sized in one dimension without adding or removing elements of the image."
    },
    {
        "question": "What is the alternative name for seam carving?",
        "answer": "The alternative name for seam carving is liquid rescaling."
    },
    {
        "question": "What is the potential drawback of using seam carving if adding or removing many pixels?",
        "answer": "If adding or removing many pixels using seam carving, the process can be very slow. It's recommended to resize the image with regular methods closer to the target size before using seam carving."
    },
    {
        "question": "What is the GitHub link to the library used in ComfyUI-seam-carving?",
        "answer": "The GitHub link to the library used in ComfyUI-seam-carving is https://github.com/li-plus/seam-carving."
    }
]