{
    "questions_and_answers": [
        {
            "question": "What is ComfyUI_SUNoise?",
            "answer": "ComfyUI_SUNoise is a feature for Scaled Uniform Noise, applicable for Ancestral and Stochastic samplers."
        },
        {
            "question": "In which GUI is ComfyUI_SUNoise implemented?",
            "answer": "ComfyUI_SUNoise is implemented in ComfyUI, a GUI that uses a stable diffusion model to generate images and videos."
        },
        {
            "question": "What is the purpose of ComfyUI_SUNoise in the context of samplers?",
            "answer": "ComfyUI_SUNoise provides Scaled Uniform Noise for both Ancestral and Stochastic samplers."
        },
        {
            "question": "Does ComfyUI_SUNoise support all types of samplers?",
            "answer": "ComfyUI_SUNoise supports two types of samplers: Ancestral and Stochastic."
        },
        {
            "question": "Is ComfyUI_SUNoise a custom node or a plugin?",
            "answer": "ComfyUI_SUNoise is not specified as a custom node or plugin in the provided document content. However, it is likely an additional feature or setting within ComfyUI itself."
        }
    ]
}