[
    {
        "question": "What are the two specialty modes mentioned in the virtuoso-nodes documentation?",
        "answer": "The two specialty modes mentioned in the virtuoso-nodes documentation are Grain Merge Mode and Grain Extract Mode."
    },
    {
        "question": "Is there an example image provided for the Grain Merge Mode?",
        "answer": "Yes, there is an example image provided for the Grain Merge Mode in the documentation."
    },
    {
        "question": "Is there an example image provided for the Grain Extract Mode?",
        "answer": "Yes, there is an example image provided for the Grain Extract Mode in the documentation."
    },
    {
        "question": "What is the file format of the example images for the specialty modes?",
        "answer": "The example images for the specialty modes are in .png format."
    },
    {
        "question": "Are the specialty modes part of the virtuoso-nodes project?",
        "answer": "Yes, the specialty modes are part of the virtuoso-nodes project, as indicated in the documentation."
    },
    {
        "question": "Is the Grain Merge Mode a feature of the virtuoso-nodes?",
        "answer": "Yes, the Grain Merge Mode is a feature of the virtuoso-nodes, as mentioned in the documentation."
    },
    {
        "question": "Is the Grain Extract Mode a feature of the virtuoso-nodes?",
        "answer": "Yes, the Grain Extract Mode is a feature of the virtuoso-nodes, as mentioned in the documentation."
    }
]