{
    "data": [
        {
            "subject": "ComfyUI Stable Video Diffusion",
            "question": "How can I install the ComfyUI Stable Video Diffusion custom node?",
            "answer": "The custom node can be installed using either the ComfyUI Manager or manually."
        },
        {
            "subject": "ComfyUI Stable Video Diffusion",
            "question": "Where can I download the models for ComfyUI Stable Video Diffusion?",
            "answer": "The models can be downloaded from the huggingface hub."
        },
        {
            "subject": "SVDModelLoader node",
            "question": "What does the SVDModelLoader node do?",
            "answer": "The SVDModelLoader node loads the Stable Video Diffusion model."
        },
        {
            "subject": "SVDSampler node",
            "question": "What is the purpose of the SVDSampler node?",
            "answer": "The SVDSampler node runs the sampling process for an input image and outputs a latent."
        },
        {
            "subject": "SVDSimpleImg2Vid node",
            "question": "What does the SVDSimpleImg2Vid node do?",
            "answer": "The SVDSimpleImg2Vid node combines the SVDModelLoader, SVDSampler, and SVDDecoder nodes into a single node."
        },
        {
            "subject": "Image to video workflow",
            "question": "How can I create an image to video workflow using ComfyUI Stable Video Diffusion?",
            "answer": "The provided workflow shows the steps to convert an image to a video using the custom node."
        },
        {
            "subject": "Image to video generation (high FPS w/ frame interpolation) workflow",
            "question": "How can I create an image to video workflow with high FPS and frame interpolation?",
            "answer": "The provided workflow shows the steps to convert an image to a video with high FPS and frame interpolation."
        }
    ]
}